demo137/__init__.py
demo137-0.1.0.dist-info/licenses/LICENSE
demo137-0.1.0.dist-info/METADATA
demo137-0.1.0.dist-info/WHEEL
demo137-0.1.0.dist-info/top_level.txt
demo137-0.1.0.dist-info/RECORD
